scibatt/__init__.py
scibatt/config.py
scibatt/filters/cycling.py
scibatt/filters/galvanostatic.py
scibatt/plotters/galvanostatic.py
scibatt/readers/biologic.py
scibatt/readers/maccor.py
scibatt-0.0.1.dist-info/METADATA
scibatt-0.0.1.dist-info/WHEEL
scibatt-0.0.1.dist-info/licenses/LICENSE
scibatt-0.0.1.dist-info/RECORD
