Metadata-Version: 2.1
Name: SciBatt
Version: 0.0.1
Summary: Read, filter and plot electrochemical data.
Project-URL: Homepage, https://github.com/amundmr/scibatt
Project-URL: Issues, https://github.com/amundmr/scibatt/issues
Author-email: Amund Raniseth <amund.raniseth@gmail.com>
License-File: LICENSE
Classifier: License :: OSI Approved :: GNU General Public License v3 or later (GPLv3+)
Classifier: Operating System :: OS Independent
Classifier: Programming Language :: Python :: 3
Requires-Python: >=3.8
